{
  "prova": "GLOSSARIO",
  "slots": {
    "GLOSSARIO_ROWS": "| custodire indizi | locuzione verbale | 保存线索；蕴含线索 | to preserve clues | potrebbe custodire indizi sull'evoluzione del linguaggio |\n| vocalizzazioni | sostantivo femminile plurale | 发声；声音表达 | vocalizations | il controllo sulle vocalizzazioni si è progressivamente affinato |\n| gettato le basi | locuzione verbale | 奠定基础 | laid the foundations | avrebbe gettato le basi del linguaggio |\n| contributi a fondo perduto | locuzione nominale | 无需偿还的补助 | non-repayable grants | 59 milioni sono destinati a contributi a fondo perduto |\n| finanziamenti agevolati | locuzione nominale | 优惠贷款 | subsidised loans | 50 milioni a finanziamenti agevolati |\n| fatturato | sostantivo | 营业额 | turnover | più del 50% del fatturato da attività turistiche |\n| fuso orario | locuzione nominale | 时差；时区差 | time difference; time zone | Il fuso orario è di due ore indietro rispetto al nostro |\n| sobborghi | nome maschile plurale | 郊区 | suburbs | giungiamo nei sobborghi di Reykjavik |\n| capolinea | nome maschile invariabile | 终点站 | terminus | al capolinea del bus |\n| ruminanti | sostantivo maschile plurale | 反刍动物 | ruminants | animali sono ruminanti |\n| isolare | verbo transitivo | 分离，提取 | to isolate | Questo DNA è difficile da isolare |\n| a giochi quasi fatti | locuzione | 在事情几乎已成定局时 | when things were almost settled | a giochi quasi fatti |\n| bocciatura | sostantivo | 淘汰；否决 | rejection | la bocciatura sul personale. |\n| spartiacque | sostantivo | 分水岭；转折点 | watershed | lo spartiacque. |\n| competenze digitali | locuzione nominale | 数字技能 | digital skills | delle competenze digitali a favore dei cittadini |\n| enti del terzo settore | locuzione nominale | 第三部门机构 | third-sector organizations | enti del terzo settore e imprese |\n| sottopassaggio | sostantivo | 地下通道 | underpass | utilizzando il sottopassaggio |\n| delega firmata | locuzione nominale | 签署的授权书 | signed authorization | la delega firmata |\n| identità digitale | locuzione nominale | 数字身份 | digital identity | Io ho aiutato il signor Paolo a creare un'identità digitale, mentre lui mi ha raccontato quanto fosse difficile chiedere assistenza a distanza. |\n| rilasciato un attestato | locuzione verbale | 颁发证书 | a certificate is issued | Vorrei inoltre sapere se il corso è gratuito e se al termine viene rilasciato un attestato. |"
  },
  "answer_slots": {},
  "key": {}
}
